{
	"errcode":0,
	"errmsg":"",
	"result":{
		"food1":{
			"title":"常见致敏食品的清单",
			"list":[
				{
					"checktype":"checkbox",
					"con":"小麦"
				},
				{
					"checktype":"checkbox",
					"con":"鸡蛋"
				},
				{
					"checktype":"checkbox",
					"con":"鱼类（包括海水鱼、淡水鱼）"
				},
				{
					"checktype":"checkbox",
					"con":"甲壳类水生动物（虾、螃蟹、蛤蜊等）"
				},
				{
					"checktype":"checkbox",
					"con":"大豆"
				},
				{
					"checktype":"checkbox",
					"con":"花生"
				},
				{
					"checktype":"checkbox",
					"con":"坚果类（杏仁、核桃、腰果、榛子、松子、栗子等）"
				},
				{
					"checktype":"checkbox",
					"con":"奶类（特别是牛奶）"
				},
				{
					"checktype":"checkbox",
					"con":"芒果"
				}


			]
		},
		"dislikefood":{
			"title":"不喜欢的食物总类",
			"list":[
				{
					"checktype":"checkbox",
					"con":"鱼"
				},
				{
					"checktype":"checkbox",
					"con":"虾"
				},
				{
					"checktype":"checkbox",
					"con":"螃蟹"
				},
				{
					"checktype":"checkbox",
					"con":"牛肉"
				},
				{
					"checktype":"checkbox",
					"con":"鸡肉"
				},
				{
					"checktype":"checkbox",
					"con":"猪肉"
				},
				{
					"checktype":"checkbox",
					"con":"羊肉"
				},
				{
					"checktype":"checkbox",
					"con":"鸡蛋"
				},
				{
					"checktype":"checkbox",
					"con":"菌藻类"
				},
				{
					"checktype":"checkbox",
					"con":"洋葱"
				},
				{
					"checktype":"checkbox",
					"con":"芹菜"
				},
				{
					"checktype":"checkbox",
					"con":"葱"
				},
				{
					"checktype":"checkbox",
					"con":"姜"
				},
				{
					"checktype":"checkbox",
					"con":"蒜"
				},
				{
					"checktype":"checkbox",
					"con":"香菜"
				},
				{
					"checktype":"checkbox",
					"con":"榴莲"
				},
				{
					"checktype":"checkbox",
					"con":"糖果"
				},
				{
					"checktype":"checkbox",
					"con":"膨化食品"
				},
				{
					"checktype":"checkbox",
					"con":"甜点"
				},
				{
					"checktype":"checkbox",
					"con":"冷饮"
				}
			]
		},
		"medicalhistory":{
			"title":"常见慢性病史",
			"list":[
				{
					"checktype":"checkbox",
					"con":"（高血压、高血糖、高血脂）"
				},
				{
					"checktype":"checkbox",
					"con":"糖尿病 "
				},
				{
					"checktype":"checkbox",
					"con":"心脏病"
				},
				{
					"checktype":"checkbox",
					"con":"冠心病"
				},
				{
					"checktype":"checkbox",
					"con":"贫血"
				},
				{
					"checktype":"checkbox",
					"con":"消化性溃疡"
				},
				{
					"checktype":"checkbox",
					"con":"类风湿性关节炎"
				},
				{
					"checktype":"checkbox",
					"con":"慢性气管炎"
				}
			]
		}
	}
}